[{"sura_id":4,"aya_id":38,"segs":[{"y":111,"x":28,"w":1295,"h":110},{"y":242,"x":31,"w":1291,"h":110},{"y":379,"x":1130,"w":193,"h":110}]},{"sura_id":4,"aya_id":39,"segs":[{"y":379,"x":30,"w":1100,"h":110},{"y":524,"x":412,"w":912,"h":110}]},{"sura_id":4,"aya_id":40,"segs":[{"y":524,"x":29,"w":383,"h":110},{"y":660,"x":28,"w":1296,"h":110},{"y":803,"x":929,"w":393,"h":110}]},{"sura_id":4,"aya_id":41,"segs":[{"y":803,"x":26,"w":903,"h":110},{"y":934,"x":516,"w":808,"h":110}]},{"sura_id":4,"aya_id":42,"segs":[{"y":934,"x":28,"w":488,"h":110},{"y":1054,"x":30,"w":1293,"h":110},{"y":1185,"x":993,"w":331,"h":110}]},{"sura_id":4,"aya_id":43,"segs":[{"y":1185,"x":28,"w":965,"h":110},{"y":1336,"x":31,"w":1291,"h":110},{"y":1467,"x":27,"w":1295,"h":110},{"y":1591,"x":28,"w":1293,"h":110},{"y":1732,"x":30,"w":1292,"h":110},{"y":1865,"x":721,"w":601,"h":110}]},{"sura_id":4,"aya_id":44,"segs":[{"y":1865,"x":29,"w":692,"h":110},{"y":2006,"x":27,"w":1297,"h":110}]}]