[{"sura_id":17,"aya_id":59,"segs":[{"y":112,"x":35,"w":1281,"h":110},{"y":252,"x":34,"w":1282,"h":110},{"y":383,"x":1016,"w":300,"h":110}]},{"sura_id":17,"aya_id":60,"segs":[{"y":383,"x":34,"w":982,"h":110},{"y":527,"x":34,"w":1282,"h":110},{"y":651,"x":35,"w":1281,"h":110}]},{"sura_id":17,"aya_id":61,"segs":[{"y":801,"x":35,"w":1281,"h":110},{"y":935,"x":580,"w":736,"h":110}]},{"sura_id":17,"aya_id":62,"segs":[{"y":935,"x":35,"w":545,"h":110},{"y":1065,"x":34,"w":1282,"h":110},{"y":1196,"x":867,"w":449,"h":110}]},{"sura_id":17,"aya_id":63,"segs":[{"y":1196,"x":34,"w":833,"h":110},{"y":1333,"x":633,"w":683,"h":110}]},{"sura_id":17,"aya_id":64,"segs":[{"y":1333,"x":35,"w":598,"h":110},{"y":1483,"x":36,"w":1280,"h":110},{"y":1603,"x":35,"w":1281,"h":110},{"y":1746,"x":1078,"w":238,"h":110}]},{"sura_id":17,"aya_id":65,"segs":[{"y":1746,"x":35,"w":1043,"h":110},{"y":1877,"x":873,"w":443,"h":110}]},{"sura_id":17,"aya_id":66,"segs":[{"y":1877,"x":35,"w":838,"h":110},{"y":2014,"x":35,"w":1281,"h":110}]}]