[{"sura_id":2,"aya_id":135,"segs":[{"y":120,"x":32,"w":1286,"h":110},{"y":250,"x":565,"w":752,"h":110}]},{"sura_id":2,"aya_id":136,"segs":[{"y":250,"x":33,"w":532,"h":110},{"y":386,"x":33,"w":1284,"h":110},{"y":528,"x":33,"w":1285,"h":110},{"y":670,"x":32,"w":1285,"h":110}]},{"sura_id":2,"aya_id":137,"segs":[{"y":801,"x":32,"w":1285,"h":110},{"y":927,"x":31,"w":1285,"h":110}]},{"sura_id":2,"aya_id":138,"segs":[{"y":1081,"x":30,"w":1289,"h":110},{"y":1195,"x":982,"w":336,"h":110}]},{"sura_id":2,"aya_id":139,"segs":[{"y":1195,"x":31,"w":951,"h":110},{"y":1328,"x":33,"w":1286,"h":110}]},{"sura_id":2,"aya_id":140,"segs":[{"y":1468,"x":33,"w":1285,"h":110},{"y":1588,"x":33,"w":1286,"h":110},{"y":1741,"x":32,"w":1285,"h":110},{"y":1873,"x":823,"w":496,"h":110}]},{"sura_id":2,"aya_id":141,"segs":[{"y":1873,"x":38,"w":785,"h":110},{"y":2002,"x":34,"w":1286,"h":110}]}]