[{"sura_id":57,"aya_id":25,"segs":[{"y":109,"x":36,"w":1279,"h":110},{"y":238,"x":35,"w":1280,"h":110},{"y":384,"x":36,"w":1279,"h":110},{"y":518,"x":691,"w":624,"h":110}]},{"sura_id":57,"aya_id":26,"segs":[{"y":518,"x":36,"w":655,"h":110},{"y":644,"x":36,"w":1279,"h":110},{"y":797,"x":572,"w":743,"h":110}]},{"sura_id":57,"aya_id":27,"segs":[{"y":797,"x":36,"w":536,"h":110},{"y":934,"x":35,"w":1280,"h":110},{"y":1058,"x":35,"w":1280,"h":110},{"y":1188,"x":35,"w":1280,"h":110},{"y":1325,"x":36,"w":1279,"h":110},{"y":1456,"x":741,"w":574,"h":110}]},{"sura_id":57,"aya_id":28,"segs":[{"y":1456,"x":36,"w":705,"h":110},{"y":1592,"x":38,"w":1277,"h":110},{"y":1730,"x":260,"w":1055,"h":110}]},{"sura_id":57,"aya_id":29,"segs":[{"y":1730,"x":35,"w":225,"h":110},{"y":1866,"x":35,"w":1277,"h":110},{"y":2000,"x":35,"w":1280,"h":110}]}]