[{"sura_id":11,"aya_id":54,"segs":[{"y":114,"x":36,"w":1279,"h":110},{"y":245,"x":475,"w":840,"h":110}]},{"sura_id":11,"aya_id":55,"segs":[{"y":245,"x":35,"w":440,"h":110},{"y":381,"x":789,"w":526,"h":110}]},{"sura_id":11,"aya_id":56,"segs":[{"y":381,"x":35,"w":754,"h":110},{"y":524,"x":41,"w":1274,"h":110}]},{"sura_id":11,"aya_id":57,"segs":[{"y":645,"x":35,"w":1280,"h":110},{"y":787,"x":41,"w":1274,"h":110}]},{"sura_id":11,"aya_id":58,"segs":[{"y":942,"x":36,"w":1279,"h":110},{"y":1068,"x":649,"w":666,"h":110}]},{"sura_id":11,"aya_id":59,"segs":[{"y":1068,"x":36,"w":613,"h":110},{"y":1189,"x":248,"w":1067,"h":110}]},{"sura_id":11,"aya_id":60,"segs":[{"y":1189,"x":35,"w":213,"h":110},{"y":1322,"x":35,"w":1280,"h":110},{"y":1463,"x":847,"w":468,"h":110}]},{"sura_id":11,"aya_id":61,"segs":[{"y":1463,"x":36,"w":811,"h":110},{"y":1590,"x":36,"w":1279,"h":110},{"y":1734,"x":41,"w":1274,"h":110}]},{"sura_id":11,"aya_id":62,"segs":[{"y":1861,"x":36,"w":1279,"h":110},{"y":2010,"x":41,"w":1274,"h":110}]}]