[{"sura_id":12,"aya_id":31,"segs":[{"y":111,"x":28,"w":1295,"h":110},{"y":239,"x":27,"w":1296,"h":110},{"y":376,"x":28,"w":1295,"h":110},{"y":514,"x":974,"w":349,"h":110}]},{"sura_id":12,"aya_id":32,"segs":[{"y":514,"x":28,"w":946,"h":110},{"y":643,"x":27,"w":1296,"h":110},{"y":791,"x":787,"w":536,"h":110}]},{"sura_id":12,"aya_id":33,"segs":[{"y":791,"x":28,"w":759,"h":110},{"y":918,"x":28,"w":1295,"h":110}]},{"sura_id":12,"aya_id":34,"segs":[{"y":1055,"x":28,"w":1295,"h":110},{"y":1179,"x":1087,"w":236,"h":110}]},{"sura_id":12,"aya_id":35,"segs":[{"y":1179,"x":27,"w":1060,"h":110},{"y":1326,"x":1040,"w":283,"h":110}]},{"sura_id":12,"aya_id":36,"segs":[{"y":1326,"x":28,"w":1012,"h":110},{"y":1444,"x":27,"w":1296,"h":110},{"y":1592,"x":27,"w":1296,"h":110},{"y":1731,"x":1000,"w":323,"h":110}]},{"sura_id":12,"aya_id":37,"segs":[{"y":1731,"x":28,"w":972,"h":110},{"y":1852,"x":28,"w":1295,"h":110},{"y":2005,"x":29,"w":1294,"h":110}]}]