[{"sura_id":51,"aya_id":31,"segs":[{"y":115,"x":573,"w":742,"h":110}]},{"sura_id":51,"aya_id":32,"segs":[{"y":115,"x":35,"w":538,"h":110},{"y":255,"x":1078,"w":238,"h":110}]},{"sura_id":51,"aya_id":33,"segs":[{"y":255,"x":395,"w":683,"h":110}]},{"sura_id":51,"aya_id":34,"segs":[{"y":255,"x":35,"w":360,"h":110},{"y":392,"x":1029,"w":287,"h":110}]},{"sura_id":51,"aya_id":35,"segs":[{"y":392,"x":246,"w":783,"h":110}]},{"sura_id":51,"aya_id":36,"segs":[{"y":392,"x":34,"w":212,"h":110},{"y":521,"x":667,"w":649,"h":110}]},{"sura_id":51,"aya_id":37,"segs":[{"y":521,"x":34,"w":633,"h":110},{"y":651,"x":926,"w":390,"h":110}]},{"sura_id":51,"aya_id":38,"segs":[{"y":651,"x":34,"w":892,"h":110},{"y":795,"x":1130,"w":186,"h":110}]},{"sura_id":51,"aya_id":39,"segs":[{"y":795,"x":398,"w":732,"h":110}]},{"sura_id":51,"aya_id":40,"segs":[{"y":795,"x":35,"w":363,"h":110},{"y":931,"x":668,"w":648,"h":110}]},{"sura_id":51,"aya_id":41,"segs":[{"y":931,"x":34,"w":634,"h":110},{"y":1065,"x":1084,"w":232,"h":110}]},{"sura_id":51,"aya_id":42,"segs":[{"y":1065,"x":35,"w":1049,"h":110}]},{"sura_id":51,"aya_id":43,"segs":[{"y":1189,"x":441,"w":875,"h":110}]},{"sura_id":51,"aya_id":44,"segs":[{"y":1189,"x":34,"w":407,"h":110},{"y":1328,"x":554,"w":762,"h":110}]},{"sura_id":51,"aya_id":45,"segs":[{"y":1328,"x":34,"w":520,"h":110},{"y":1464,"x":798,"w":518,"h":110}]},{"sura_id":51,"aya_id":46,"segs":[{"y":1464,"x":34,"w":764,"h":110},{"y":1594,"x":1071,"w":245,"h":110}]},{"sura_id":51,"aya_id":47,"segs":[{"y":1594,"x":230,"w":841,"h":110}]},{"sura_id":51,"aya_id":48,"segs":[{"y":1594,"x":35,"w":195,"h":110},{"y":1741,"x":723,"w":593,"h":110}]},{"sura_id":51,"aya_id":49,"segs":[{"y":1741,"x":35,"w":688,"h":110},{"y":1865,"x":930,"w":386,"h":110}]},{"sura_id":51,"aya_id":50,"segs":[{"y":1865,"x":34,"w":896,"h":110}]},{"sura_id":51,"aya_id":51,"segs":[{"y":1998,"x":33,"w":1283,"h":110}]}]